linkdin/__init__.py
linkdin-0.1.0.dist-info/METADATA
linkdin-0.1.0.dist-info/WHEEL
linkdin-0.1.0.dist-info/top_level.txt
linkdin-0.1.0.dist-info/RECORD
