Metadata-Version: 2.4
Name: linkdin
Version: 0.1.0
Summary: linkedin new module creating
Author: linkdin-admin
Author-email: sathishdhuda25@gmail.com
Classifier: Programming Language :: Python :: 3
Classifier: License :: OSI Approved :: MIT License
Classifier: Operating System :: OS Independent
Requires-Python: >=3.6
Dynamic: author
Dynamic: author-email
Dynamic: classifier
Dynamic: requires-python
Dynamic: summary
